README.md
setup.cfg
setup.py
resview_client/__init__.py
resview_client/api_client.py
resview_client/configuration.py
resview_client/exceptions.py
resview_client/model_utils.py
resview_client/rest.py
resview_client/resview_api.py
resview_client/api/__init__.py
resview_client/api/reservations_api.py
resview_client/apis/__init__.py
resview_client/model/__init__.py
resview_client/model/http_validation_error.py
resview_client/model/location_inner.py
resview_client/model/reservation_batch_get_request.py
resview_client/model/validation_error.py
resview_client/models/__init__.py
resview_client_python.egg-info/PKG-INFO
resview_client_python.egg-info/SOURCES.txt
resview_client_python.egg-info/dependency_links.txt
resview_client_python.egg-info/requires.txt
resview_client_python.egg-info/top_level.txt
test/test_http_validation_error.py
test/test_location_inner.py
test/test_reservation_batch_get_request.py
test/test_reservations_api.py
test/test_validation_error.py