Metadata-Version: 2.1
Name: resview-client-python
Version: 0.2.0
Summary: Hwmux reservations MV API
Home-page: 
Author: OpenAPI Generator community
Author-email: team@openapitools.org
Keywords: OpenAPI,OpenAPI-Generator,Hwmux reservations MV API
Requires-Python: >=3.6
